maninex/__init__.py
maninex/maninex.py
maninex-0.4.dist-info/DESCRIPTION.rst
maninex-0.4.dist-info/METADATA
maninex-0.4.dist-info/RECORD
maninex-0.4.dist-info/WHEEL
maninex-0.4.dist-info/entry_points.txt
maninex-0.4.dist-info/metadata.json
maninex-0.4.dist-info/top_level.txt
