Metadata-Version: 2.0
Name: maninex
Version: 0.4
Summary: An extension manager to replace Google's WebStore
Home-page: https://github.com/InspectorMustache/maninex
Author: Pu Anlai
Author-email: UNKNOWN
License: MIT
Keywords: chromium extension webstore inox iridium
Platform: UNKNOWN
Classifier: Development Status :: 3 - Alpha
Classifier: Intended Audience :: End Users/Desktop
Classifier: Topic :: Internet :: WWW/HTTP :: Browsers
Classifier: License :: OSI Approved :: MIT License
Classifier: Programming Language :: Python :: 3 :: Only
Requires-Python: >=3.5
Requires-Dist: requests
